bumpdeps.py
bumpdeps-0.2.1.dist-info/LICENSE
bumpdeps-0.2.1.dist-info/METADATA
bumpdeps-0.2.1.dist-info/WHEEL
bumpdeps-0.2.1.dist-info/entry_points.txt
bumpdeps-0.2.1.dist-info/top_level.txt
bumpdeps-0.2.1.dist-info/RECORD
