Metadata-Version: 2.1
Name: bumpdeps
Version: 0.2.1
Summary: Utility for bumping dependency versions specified in pyproject.toml files
Author-email: Avram Lubkin <avylove@rockhopper.net>
License: MPLv2.0
Project-URL: Homepage, https://github.com/Rockhopper-Technologies/bumpdeps
Keywords: bump,dependency,dependencies,versions,extras
Classifier: Programming Language :: Python :: 3
Classifier: Development Status :: 4 - Beta
Classifier: Environment :: Console
Classifier: Intended Audience :: Developers
Classifier: License :: OSI Approved :: Mozilla Public License 2.0 (MPL 2.0)
Classifier: Topic :: Software Development
Requires-Python: >=3.7
License-File: LICENSE
Requires-Dist: packaging
Requires-Dist: requests
Requires-Dist: tomlkit
Provides-Extra: tests
Requires-Dist: responses ; extra == 'tests'
